pose_labelbox/__init__.py
pose_labelbox/alphapose.py
pose_labelbox/core.py
pose_labelbox/labelbox.py
pose_labelbox/overlay.py
pose_labelbox/process_video.py
pose_labelbox/utils.py
wf_pose_labelbox-0.2.0.dist-info/LICENSE
wf_pose_labelbox-0.2.0.dist-info/WHEEL
wf_pose_labelbox-0.2.0.dist-info/METADATA
wf_pose_labelbox-0.2.0.dist-info/RECORD
